html_elements/__init__.py
html_elements/base.py
html_elements/elements.py
html_elements/extensions.py
html_elements/py.typed
html_elements-0.2.1.dist-info/LICENSE
html_elements-0.2.1.dist-info/METADATA
html_elements-0.2.1.dist-info/WHEEL
html_elements-0.2.1.dist-info/RECORD
