Metadata-Version: 2.1
Name: html-elements
Version: 0.2.1
Summary: HTML element objects to use in pure Python server side rendering
License: MIT
Author: Anton De Meester
Author-email: antondemeester@gmail.com
Requires-Python: >=3.8,<4.0
Classifier: License :: OSI Approved :: MIT License
Classifier: Programming Language :: Python :: 3
Classifier: Programming Language :: Python :: 3.8
Classifier: Programming Language :: Python :: 3.9
Classifier: Programming Language :: Python :: 3.10
Classifier: Programming Language :: Python :: 3.11
Classifier: Programming Language :: Python :: 3.12
